README.rst
setup.cfg
setup.py
request_validator/__init__.py
request_validator/fields.py
request_validator/serializers.py
request_validator/validator.py
request_validator.egg-info/PKG-INFO
request_validator.egg-info/SOURCES.txt
request_validator.egg-info/dependency_links.txt
request_validator.egg-info/top_level.txt