Metadata-Version: 1.1
Name: request-validator
Version: 2.0.5
Summary: Python request validator
Home-page: https://github.com/amirasaran/request_validator
Author: Amir Mohsen Asaran
Author-email: admin@mihanmail.com
License: MIT
Keywords: request validator
Platform: UNKNOWN
Classifier: Development Status :: 3 - Alpha
Classifier: Intended Audience :: Developers
Classifier: Topic :: Software Development :: Build Tools
Classifier: License :: OSI Approved :: MIT License
Classifier: Programming Language :: Python :: 2
Classifier: Programming Language :: Python :: 2.7
Classifier: Programming Language :: Python :: 3
Classifier: Programming Language :: Python :: 3.3
Classifier: Programming Language :: Python :: 3.4
Classifier: Programming Language :: Python :: 3.5
